rkale/__init__.py
rkale/config.py
rkale/exceptions.py
rkale/operations.py
rkale/project_operations.py
rkale/rkale.py
rkale/utils.py
rkale-1.0.3.dist-info/entry_points.txt
rkale-1.0.3.dist-info/WHEEL
rkale-1.0.3.dist-info/METADATA
rkale-1.0.3.dist-info/RECORD
