Metadata-Version: 2.1
Name: rkale
Version: 1.0.3
Summary: Rclone wrapper to manage multiple datasets in a project
Home-page: https://github.com/nextml-code/rkale
License: MIT
Author: nextml
Author-email: joar@nextml.com
Requires-Python: >=3.7,<4.0
Classifier: License :: OSI Approved :: MIT License
Classifier: Programming Language :: Python :: 3
Classifier: Programming Language :: Python :: 3.7
Classifier: Programming Language :: Python :: 3.8
Classifier: Programming Language :: Python :: 3.9
Classifier: Programming Language :: Python :: 3.10
Requires-Dist: toml (>=0.10.2,<0.11.0)
Requires-Dist: tqdm (>=4.60.0,<5.0.0)
Project-URL: Repository, https://github.com/nextml-code/rkale
